s360/__init__.py
s360-0.0.1.dist-info/LICENSE
s360-0.0.1.dist-info/METADATA
s360-0.0.1.dist-info/WHEEL
s360-0.0.1.dist-info/entry_points.txt
s360-0.0.1.dist-info/top_level.txt
s360-0.0.1.dist-info/RECORD
