Metadata-Version: 2.1
Name: s360
Version: 0.0.1
Summary: IBM System/360 Emulator
Home-page: https://github.com/metebalci/s360
Author: Mete Balci
Author-email: metebalci@gmail.com
Classifier: License :: OSI Approved :: GNU General Public License v3 (GPLv3)
Classifier: Operating System :: OS Independent
Classifier: Programming Language :: Python :: 3
Classifier: Topic :: System :: Emulators
Requires-Python: >=3.10
License-File: LICENSE
